emsm/__init__.py
emsm/requirements.txt
emsm/core/__init__.py
emsm/core/application.py
emsm/core/argparse_.py
emsm/core/base_plugin.py
emsm/core/conf.py
emsm/core/initd_script.sh
emsm/core/license_.py
emsm/core/logging_.py
emsm/core/paths.py
emsm/core/plugins.py
emsm/core/server.py
emsm/core/version.py
emsm/core/worlds.py
emsm/core/lib/__init__.py
emsm/core/lib/userinput.py
emsm/plugins/__init__.py
emsm/plugins/backups.py
emsm/plugins/emsm.py
emsm/plugins/guard.py
emsm/plugins/hellodolly.py
emsm/plugins/initd.py
emsm/plugins/plugins.py
emsm/plugins/server.py
emsm/plugins/worlds.py
emsm-6.0.2b0.dist-info/METADATA
emsm-6.0.2b0.dist-info/RECORD
emsm-6.0.2b0.dist-info/WHEEL
emsm-6.0.2b0.dist-info/top_level.txt
