Metadata-Version: 2.1
Name: emsm
Version: 6.0.2b0
Summary: A lightweight, easy to extend mineraft server manager
Home-page: https://github.com/benediktschmitt/emsm
Author: The EMSM authors (see AUTHORS.txt)
Author-email: UNKNOWN
License: MIT License
Platform: LINUX
Classifier: Development Status :: 4 - Beta
Classifier: Environment :: Console
Classifier: License :: OSI Approved :: MIT License
Classifier: Operating System :: POSIX :: Linux
Classifier: Programming Language :: Python :: 3.2
Classifier: Topic :: Games/Entertainment
Classifier: Topic :: System :: Systems Administration
Classifier: Topic :: Utilities
Requires-Dist: blinker
Requires-Dist: filelock
Requires-Dist: colorama
Requires-Dist: termcolor
Requires-Dist: pyyaml
